booli_crawler/__init__.py
booli_crawler/crawler.py
booli_crawler/parser.py
booli_crawler/sold_listing_list.py
booli_crawler/sold_listings.py
booli_crawler/types.py
booli_crawler/url.py
booli_crawler-1.0.2.dist-info/LICENSE
booli_crawler-1.0.2.dist-info/METADATA
booli_crawler-1.0.2.dist-info/WHEEL
booli_crawler-1.0.2.dist-info/top_level.txt
booli_crawler-1.0.2.dist-info/RECORD
